csirtg_indicator/__init__.py
csirtg_indicator/_version.py
csirtg_indicator/constants.py
csirtg_indicator/exceptions.py
csirtg_indicator/indicator.py
csirtg_indicator/utils.py
csirtg_indicator/format/__init__.py
csirtg_indicator/format/plugin.py
csirtg_indicator/format/zbind.py
csirtg_indicator/format/zbro.py
csirtg_indicator/format/zcsv.py
csirtg_indicator/format/zjson.py
csirtg_indicator/format/zsnort.py
csirtg_indicator/format/zstix.py
csirtg_indicator/format/ztable.py
csirtg_indicator-0.0.0a20.dist-info/DESCRIPTION.rst
csirtg_indicator-0.0.0a20.dist-info/METADATA
csirtg_indicator-0.0.0a20.dist-info/RECORD
csirtg_indicator-0.0.0a20.dist-info/WHEEL
csirtg_indicator-0.0.0a20.dist-info/entry_points.txt
csirtg_indicator-0.0.0a20.dist-info/metadata.json
csirtg_indicator-0.0.0a20.dist-info/top_level.txt
test/__init__.py
test/test_email.py
test/test_fqdn.py
test/test_indicator.py
test/test_ipv4.py
test/test_ipv6.py
test/test_message.py
test/test_urls.py
test/format/__init__.py
test/format/test_bind.py
test/format/test_bro.py
test/format/test_csv.py
test/format/test_json.py
test/format/test_snort.py
test/format/test_stix.py
test/format/test_table.py
