Metadata-Version: 2.0
Name: csirtg-indicator
Version: 0.0.0a20
Summary: CSIRTG Indicator Framework
Home-page: https://github.com/csirtgadgets/csirtg-indicator-py
Author: Wes Young
Author-email: wes@csirtgadgets.org
License: LGPL3
Keywords: network,security
Platform: UNKNOWN
Classifier: Topic :: System :: Networking
Classifier: Environment :: Other Environment
Classifier: Intended Audience :: Developers
Classifier: License :: OSI Approved :: GNU Lesser General Public License v3 (LGPLv3)
Classifier: Programming Language :: Python
Requires-Dist: arrow (>=0.7.0)
Requires-Dist: ipaddress (>=1.0.16)
Requires-Dist: pendulum (>=0.5.2)
Requires-Dist: prettytable (>=0.7.2)
Requires-Dist: pytricia (>=0.9.0)
